{"2017-12":[{"title":"Eralng系列文章","date":"2017-12-24T15:29:53.000Z","link":"/2017/12/24/Erlang/"},{"title":"Erlang to Elixir","date":"2017-12-24T15:29:53.000Z","link":"/2017/12/24/Erlang2Elixir/"},{"title":"Erlang Garbage Collection","date":"2017-12-24T15:29:53.000Z","link":"/2017/12/24/ErlangGarbageCollection/"},{"title":"Erlang Scheduler","date":"2017-12-24T15:29:53.000Z","link":"/2017/12/24/ErlangScheduler/"},{"title":"Memory Allocator","date":"2017-12-24T15:29:53.000Z","link":"/2017/12/24/ErlangMemoryAllocator/"},{"title":"Erlang节点互联","date":"2017-12-24T15:29:53.000Z","link":"/2017/12/24/ErlangNodeConnect/"},{"title":"Erlang Process","date":"2017-12-24T15:29:53.000Z","link":"/2017/12/24/ErlangProcess/"},{"title":"Erlang 读书笔记","date":"2017-12-24T15:29:53.000Z","link":"/2017/12/24/ReadingNotes/"},{"title":"Erlang 虚拟机内的内存管理","date":"2017-12-24T15:29:53.000Z","link":"/2017/12/24/zhengsyao_Erlang 虚拟机内的内存管理（Lukas Larsson演讲听写稿）/"}],"2021-6":[{"title":"项目往事之团队","date":"2021-06-01T10:59:34.000Z","link":"/2021/06/01/project-member/"}],"2021-7":[{"title":"数据库之分区、分片、分表","date":"2021-07-12T09:13:47.000Z","link":"/2021/07/12/database-sharding-partitioning/"}],"2022-4":[{"title":"数据驱动类技能","date":"2022-04-07T15:29:53.000Z","link":"/2022/04/07/GameSkill/"}],"2022-12":[{"title":"游戏服务器开发与运维","date":"2022-12-21T01:57:03.000Z","link":"/2022/12/21/gameserver/"}]}